CHANGES.txt
LICENSE.txt
MANIFEST.in
README.txt
setup.py
PRC.egg-info/PKG-INFO
PRC.egg-info/SOURCES.txt
PRC.egg-info/dependency_links.txt
PRC.egg-info/requires.txt
PRC.egg-info/top_level.txt
bin/example_prcclient.py
bin/example_prcserver.py
prc/__init__.py
prc/prc.py
prc/prcclient.py
prc/prcserver.py
prc/comm/__init__.py
prc/comm/comm.py
prc/comm/commclient.py
prc/comm/commserver.py
prc/comm/protocol.py
prc/test/__init__.py
prc/test/prc_test.py