Metadata-Version: 1.1
Name: PRC
Version: 1.0.0
Summary: Python Remote Console
Home-page: http://pypi.python.org/pypi/prc/
Author: Damian Nowok
Author-email: damian.nowok@gmail.com
License: LICENSE.txt
Platform: UNKNOWN
Classifier: Programming Language :: Python :: 3
